setup.py
py_cloudwatch.egg-info/PKG-INFO
py_cloudwatch.egg-info/SOURCES.txt
py_cloudwatch.egg-info/dependency_links.txt
py_cloudwatch.egg-info/top_level.txt
pycloudwatch/__init__.py
pycloudwatch/sender.py