Metadata-Version: 1.0
Name: py-cloudwatch
Version: 0.0.1
Summary: Python modules for sending metrics to cloudwatch.
Home-page: https://github.com/blacked/py-cloudwatch
Author: Alexey Dubkov
Author-email: alexey.dubkov@gmail.com
License: UNKNOWN
Platform: UNKNOWN
